messenger_utils/__init__.py
messenger_utils/__main__.py
messenger_utils/cli.py
messenger_utils/max/__init__.py
messenger_utils/max/max_keyboard.py
messenger_utils/max/max_receiver.py
messenger_utils/max/max_sender.py
messenger_utils/models/webhook_event.py
messenger_utils/py.typed
messenger_utils/receiver.py
messenger_utils/sender.py
messenger_utils/telegram/__init__.py
messenger_utils-2.1.3.dist-info/WHEEL
messenger_utils-2.1.3.dist-info/METADATA
messenger_utils-2.1.3.dist-info/RECORD
