Metadata-Version: 2.3
Name: messenger-utils
Version: 2.1.3
Summary: Utilites and CLI for MAX and Telegram messengers.
Keywords: messenger,telegram,max,webhooks,bot
Author: Maxim Huzmiev
Author-email: Maxim Huzmiev <max@huzm.ru>
Classifier: Programming Language :: Python :: 3.12
Classifier: Intended Audience :: Developers
Classifier: Operating System :: OS Independent
Classifier: Development Status :: 4 - Beta
Requires-Dist: httpx>=0.28.1
Requires-Dist: loguru>=0.7.3
Requires-Dist: pydantic-settings>=2.12.0
Requires-Dist: typer>=0.20.0
Requires-Python: >=3.12
Project-URL: Changelog, https://github.com/maxhuzm/messenger-utils/blob/master/CHANGELOG.md
Project-URL: Documentation, https://github.com/maxhuzm/messenger-utils/blob/master/README.md
Project-URL: Repository, https://github.com/maxhuzm/messenger-utils
